sro2syllabics/__init__.py
sro2syllabics-0.1.0.dist-info/entry_points.txt
sro2syllabics-0.1.0.dist-info/WHEEL
sro2syllabics-0.1.0.dist-info/METADATA
sro2syllabics-0.1.0.dist-info/RECORD
